<?xml version='1.0' encoding='UTF-8' standalone='yes'?>
<package version="0">
 <meta>
  <uuid>15a6f592-6c00-4c56-89d9-439f88073fb2</uuid>
  <version>0.1</version>
  <author>LibrePCB</author>
  <created>2015-12-21T13:28:18Z</created>
  <last_modified>2015-12-21T13:28:18Z</last_modified>
  <name locale="en_US">SMK</name>
  <description locale="en_US">

This element was automatically imported from Eagle
Filepath: isabellen.lbr
Name: SMK
NOTE: Remove this text after manual rework!</description>
  <keywords locale="en_US"></keywords>
 </meta>
 <pads>
  <pad uuid="920a8be0-72a5-4a2f-a438-82105c8569da">2</pad>
  <pad uuid="598ae543-3f62-4b9c-8a43-ae0c39112a12">1</pad>
 </pads>
 <footprints default="e115eed0-96e6-4d73-9f9b-b4c7b48d557c">
  <footprint uuid="e115eed0-96e6-4d73-9f9b-b4c7b48d557c">
   <name locale="en_US">default</name>
   <description locale="en_US"></description>
   <geometry>
    <polygon fill="false" layer="200" grab_area="true" start_x="1.400000" start_y="-0.650000" width="0.200000">
     <segment end_x="1.400000" end_y="0.650000" angle="0.000000"/>
     <segment end_x="-1.400000" end_y="0.650000" angle="0.000000"/>
     <segment end_x="-1.400000" end_y="-0.650000" angle="0.000000"/>
     <segment end_x="1.400000" end_y="-0.650000" angle="0.000000"/>
    </polygon>
    <text layer="240" height="2.500000" h_align="left" rotation="0.000000" v_align="bottom" x="-2.692400" y="1.066800">${CMP::NAME}</text>
    <text layer="250" height="2.000000" h_align="left" rotation="0.000000" v_align="bottom" x="-2.692400" y="-2.336800">${CMP::VALUE}</text>
    <pad type="smt_rect" height="2.000000" smt_side="top" width="2.500000" uuid="920a8be0-72a5-4a2f-a438-82105c8569da" rotation="0.000000" tht_drill="0.000000" x="-1.524000" y="0.000000"/>
    <pad type="smt_rect" height="2.000000" smt_side="top" width="2.500000" uuid="598ae543-3f62-4b9c-8a43-ae0c39112a12" rotation="0.000000" tht_drill="0.000000" x="1.524000" y="0.000000"/>
   </geometry>
  </footprint>
 </footprints>
</package>
