<?xml version='1.0' encoding='UTF-8' standalone='yes'?>
<package version="0">
 <meta>
  <uuid>89a8125d-98fc-4e86-9953-6c2461cff096</uuid>
  <version>0.1</version>
  <author>LibrePCB</author>
  <created>2015-12-21T13:40:32Z</created>
  <last_modified>2015-12-21T13:40:32Z</last_modified>
  <name locale="en_US">52745-0990</name>
  <description locale="en_US">&lt;b>FFC/FPC&lt;/b>-to-Board  0.50mm (.020") SMT Top Contact&lt;p>
Right Angle, ZIF, Style Receptacle 52745 / 52435&lt;br>
Source: http://www.molex.com/product/ffc/52745.html

This element was automatically imported from Eagle
Filepath: con-molex.lbr
Name: 52745-0990
NOTE: Remove this text after manual rework!</description>
  <keywords locale="en_US"></keywords>
 </meta>
 <pads>
  <pad uuid="0fb080ec-e02c-481d-8cb6-83b3d9ecc712">1</pad>
  <pad uuid="98a572e0-08a1-49eb-b899-615c5ecd76ef">2</pad>
  <pad uuid="eee4a569-1423-4c2d-9809-6bd5a86bb5f2">3</pad>
  <pad uuid="eb7010a3-1e93-44b8-8425-d56328a282f2">4</pad>
  <pad uuid="bdd0e33a-1261-4e7e-bec9-f5c49a935fe1">5</pad>
  <pad uuid="abde0033-cfdb-4d48-8ea4-52fefecf4346">6</pad>
  <pad uuid="f705a7b5-818c-49d7-a918-6da24a756cdc">7</pad>
  <pad uuid="4407dd8e-b1ca-46a5-8e4a-3262d76e4e5c">8</pad>
  <pad uuid="20401992-0b8f-4b57-acbf-b82c2c710a41">9</pad>
 </pads>
 <footprints default="0ec11fb2-cabc-4fb3-af9e-b25f165b230e">
  <footprint uuid="0ec11fb2-cabc-4fb3-af9e-b25f165b230e">
   <name locale="en_US">default</name>
   <description locale="en_US"></description>
   <geometry>
    <polygon fill="false" layer="260" grab_area="true" start_x="-5.200000" start_y="-3.000000" width="0.203200">
     <segment end_x="-5.200000" end_y="-3.500000" angle="0.000000"/>
    </polygon>
    <polygon fill="false" layer="260" grab_area="true" start_x="-5.200000" start_y="-3.500000" width="0.203200">
     <segment end_x="-5.100000" end_y="-3.600000" angle="0.000000"/>
    </polygon>
    <polygon fill="false" layer="260" grab_area="true" start_x="-5.100000" start_y="-3.600000" width="0.203200">
     <segment end_x="5.100000" end_y="-3.600000" angle="0.000000"/>
    </polygon>
    <polygon fill="false" layer="260" grab_area="true" start_x="5.100000" start_y="-3.600000" width="0.203200">
     <segment end_x="5.200000" end_y="-3.500000" angle="0.000000"/>
    </polygon>
    <polygon fill="false" layer="260" grab_area="true" start_x="5.200000" start_y="-3.500000" width="0.203200">
     <segment end_x="5.200000" end_y="-3.000000" angle="0.000000"/>
    </polygon>
    <polygon fill="false" layer="260" grab_area="true" start_x="5.200000" start_y="-3.000000" width="0.203200">
     <segment end_x="-5.200000" end_y="-3.000000" angle="0.000000"/>
    </polygon>
    <polygon fill="false" layer="260" grab_area="true" start_x="-3.750000" start_y="-1.500000" width="0.203200">
     <segment end_x="-3.750000" end_y="-2.900000" angle="0.000000"/>
    </polygon>
    <polygon fill="false" layer="260" grab_area="true" start_x="3.750000" start_y="-1.500000" width="0.203200">
     <segment end_x="3.750000" end_y="-2.900000" angle="0.000000"/>
    </polygon>
    <polygon fill="false" layer="260" grab_area="true" start_x="-2.300000" start_y="-3.100000" width="0.101600">
     <segment end_x="-2.300000" end_y="-3.500000" angle="0.000000"/>
    </polygon>
    <polygon fill="false" layer="260" grab_area="true" start_x="-2.300000" start_y="-3.500000" width="0.101600">
     <segment end_x="-2.050000" end_y="-3.250000" angle="0.000000"/>
    </polygon>
    <polygon fill="false" layer="260" grab_area="true" start_x="-2.050000" start_y="-3.250000" width="0.101600">
     <segment end_x="-2.050000" end_y="-3.100000" angle="0.000000"/>
    </polygon>
    <polygon fill="false" layer="260" grab_area="true" start_x="2.050000" start_y="-3.100000" width="0.101600">
     <segment end_x="2.050000" end_y="-3.250000" angle="0.000000"/>
    </polygon>
    <polygon fill="false" layer="260" grab_area="true" start_x="2.050000" start_y="-3.250000" width="0.101600">
     <segment end_x="2.300000" end_y="-3.500000" angle="0.000000"/>
    </polygon>
    <polygon fill="false" layer="260" grab_area="true" start_x="2.300000" start_y="-3.500000" width="0.101600">
     <segment end_x="2.300000" end_y="-3.100000" angle="0.000000"/>
    </polygon>
    <polygon fill="false" layer="200" grab_area="true" start_x="4.450000" start_y="1.950000" width="0.101600">
     <segment end_x="4.600000" end_y="1.950000" angle="0.000000"/>
    </polygon>
    <polygon fill="false" layer="200" grab_area="true" start_x="4.600000" start_y="1.950000" width="0.101600">
     <segment end_x="4.600000" end_y="1.650000" angle="0.000000"/>
    </polygon>
    <polygon fill="false" layer="200" grab_area="true" start_x="4.600000" start_y="1.650000" width="0.101600">
     <segment end_x="5.200000" end_y="1.650000" angle="0.000000"/>
    </polygon>
    <polygon fill="false" layer="200" grab_area="true" start_x="5.200000" start_y="1.650000" width="0.101600">
     <segment end_x="5.200000" end_y="1.450000" angle="0.000000"/>
    </polygon>
    <polygon fill="false" layer="200" grab_area="true" start_x="5.200000" start_y="1.450000" width="0.101600">
     <segment end_x="4.600000" end_y="1.450000" angle="0.000000"/>
    </polygon>
    <polygon fill="false" layer="200" grab_area="true" start_x="4.600000" start_y="1.450000" width="0.101600">
     <segment end_x="4.600000" end_y="0.950000" angle="0.000000"/>
    </polygon>
    <polygon fill="false" layer="200" grab_area="true" start_x="4.600000" start_y="0.950000" width="0.101600">
     <segment end_x="4.650000" end_y="0.900000" angle="0.000000"/>
    </polygon>
    <polygon fill="false" layer="200" grab_area="true" start_x="4.650000" start_y="0.900000" width="0.101600">
     <segment end_x="5.200000" end_y="0.900000" angle="0.000000"/>
    </polygon>
    <polygon fill="false" layer="200" grab_area="true" start_x="5.200000" start_y="0.900000" width="0.101600">
     <segment end_x="5.200000" end_y="0.700000" angle="0.000000"/>
    </polygon>
    <polygon fill="false" layer="200" grab_area="true" start_x="5.200000" start_y="0.700000" width="0.101600">
     <segment end_x="4.450000" end_y="0.700000" angle="0.000000"/>
    </polygon>
    <polygon fill="false" layer="200" grab_area="true" start_x="4.450000" start_y="0.700000" width="0.101600">
     <segment end_x="4.450000" end_y="1.900000" angle="0.000000"/>
    </polygon>
    <polygon fill="false" layer="200" grab_area="true" start_x="-4.450000" start_y="1.950000" width="0.101600">
     <segment end_x="-4.600000" end_y="1.950000" angle="0.000000"/>
    </polygon>
    <polygon fill="false" layer="200" grab_area="true" start_x="-4.600000" start_y="1.950000" width="0.101600">
     <segment end_x="-4.600000" end_y="1.650000" angle="0.000000"/>
    </polygon>
    <polygon fill="false" layer="200" grab_area="true" start_x="-4.600000" start_y="1.650000" width="0.101600">
     <segment end_x="-5.200000" end_y="1.650000" angle="0.000000"/>
    </polygon>
    <polygon fill="false" layer="200" grab_area="true" start_x="-5.200000" start_y="1.650000" width="0.101600">
     <segment end_x="-5.200000" end_y="1.450000" angle="0.000000"/>
    </polygon>
    <polygon fill="false" layer="200" grab_area="true" start_x="-5.200000" start_y="1.450000" width="0.101600">
     <segment end_x="-4.600000" end_y="1.450000" angle="0.000000"/>
    </polygon>
    <polygon fill="false" layer="200" grab_area="true" start_x="-4.600000" start_y="1.450000" width="0.101600">
     <segment end_x="-4.600000" end_y="0.950000" angle="0.000000"/>
    </polygon>
    <polygon fill="false" layer="200" grab_area="true" start_x="-4.600000" start_y="0.950000" width="0.101600">
     <segment end_x="-4.650000" end_y="0.900000" angle="0.000000"/>
    </polygon>
    <polygon fill="false" layer="200" grab_area="true" start_x="-4.650000" start_y="0.900000" width="0.101600">
     <segment end_x="-5.200000" end_y="0.900000" angle="0.000000"/>
    </polygon>
    <polygon fill="false" layer="200" grab_area="true" start_x="-5.200000" start_y="0.900000" width="0.101600">
     <segment end_x="-5.200000" end_y="0.700000" angle="0.000000"/>
    </polygon>
    <polygon fill="false" layer="200" grab_area="true" start_x="-5.200000" start_y="0.700000" width="0.101600">
     <segment end_x="-4.450000" end_y="0.700000" angle="0.000000"/>
    </polygon>
    <polygon fill="false" layer="200" grab_area="true" start_x="-4.450000" start_y="0.700000" width="0.101600">
     <segment end_x="-4.450000" end_y="1.900000" angle="0.000000"/>
    </polygon>
    <polygon fill="false" layer="260" grab_area="true" start_x="-2.900000" start_y="-1.250000" width="0.203200">
     <segment end_x="-2.900000" end_y="1.000000" angle="0.000000"/>
    </polygon>
    <polygon fill="false" layer="260" grab_area="true" start_x="-2.900000" start_y="1.000000" width="0.203200">
     <segment end_x="-2.750000" end_y="1.000000" angle="-180.000000"/>
    </polygon>
    <polygon fill="false" layer="260" grab_area="true" start_x="-2.750000" start_y="1.000000" width="0.203200">
     <segment end_x="-2.750000" end_y="-1.250000" angle="0.000000"/>
    </polygon>
    <polygon fill="false" layer="260" grab_area="true" start_x="2.750000" start_y="-1.250000" width="0.203200">
     <segment end_x="2.750000" end_y="1.000000" angle="0.000000"/>
    </polygon>
    <polygon fill="false" layer="260" grab_area="true" start_x="2.750000" start_y="1.000000" width="0.203200">
     <segment end_x="2.900000" end_y="1.000000" angle="-180.000000"/>
    </polygon>
    <polygon fill="false" layer="260" grab_area="true" start_x="2.900000" start_y="1.000000" width="0.203200">
     <segment end_x="2.900000" end_y="-1.250000" angle="0.000000"/>
    </polygon>
    <polygon fill="true" layer="270" grab_area="true" start_x="4.500000" start_y="-0.200000" width="0.000000">
     <segment end_x="5.650000" end_y="-0.200000" angle="0.000000"/>
     <segment end_x="5.650000" end_y="2.000000" angle="0.000000"/>
     <segment end_x="4.500000" end_y="2.000000" angle="0.000000"/>
     <segment end_x="4.500000" end_y="-0.200000" angle="0.000000"/>
    </polygon>
    <polygon fill="true" layer="270" grab_area="true" start_x="3.250000" start_y="-1.050000" width="0.000000">
     <segment end_x="4.550000" end_y="-1.050000" angle="0.000000"/>
     <segment end_x="4.550000" end_y="2.000000" angle="0.000000"/>
     <segment end_x="3.250000" end_y="2.000000" angle="0.000000"/>
     <segment end_x="3.250000" end_y="-1.050000" angle="0.000000"/>
    </polygon>
    <polygon fill="true" layer="230" grab_area="true" start_x="3.450000" start_y="-0.050000" width="0.000000">
     <segment end_x="5.450000" end_y="-0.050000" angle="0.000000"/>
     <segment end_x="5.450000" end_y="1.850000" angle="0.000000"/>
     <segment end_x="3.450000" end_y="1.850000" angle="0.000000"/>
     <segment end_x="3.450000" end_y="-0.050000" angle="0.000000"/>
    </polygon>
    <polygon fill="true" layer="270" grab_area="true" start_x="-5.650000" start_y="-0.200000" width="0.000000">
     <segment end_x="-4.500000" end_y="-0.200000" angle="0.000000"/>
     <segment end_x="-4.500000" end_y="2.000000" angle="0.000000"/>
     <segment end_x="-5.650000" end_y="2.000000" angle="0.000000"/>
     <segment end_x="-5.650000" end_y="-0.200000" angle="0.000000"/>
    </polygon>
    <polygon fill="true" layer="270" grab_area="true" start_x="-4.550000" start_y="-1.050000" width="0.000000">
     <segment end_x="-3.250000" end_y="-1.050000" angle="0.000000"/>
     <segment end_x="-3.250000" end_y="2.000000" angle="0.000000"/>
     <segment end_x="-4.550000" end_y="2.000000" angle="0.000000"/>
     <segment end_x="-4.550000" end_y="-1.050000" angle="0.000000"/>
    </polygon>
    <polygon fill="true" layer="230" grab_area="true" start_x="-5.450000" start_y="-0.050000" width="0.000000">
     <segment end_x="-3.450000" end_y="-0.050000" angle="0.000000"/>
     <segment end_x="-3.450000" end_y="1.850000" angle="0.000000"/>
     <segment end_x="-5.450000" end_y="1.850000" angle="0.000000"/>
     <segment end_x="-5.450000" end_y="-0.050000" angle="0.000000"/>
    </polygon>
    <polygon fill="true" layer="200" grab_area="true" start_x="-2.100000" start_y="2.000000" width="0.000000">
     <segment end_x="-1.900000" end_y="2.000000" angle="0.000000"/>
     <segment end_x="-1.900000" end_y="2.700000" angle="0.000000"/>
     <segment end_x="-2.100000" end_y="2.700000" angle="0.000000"/>
     <segment end_x="-2.100000" end_y="2.000000" angle="0.000000"/>
    </polygon>
    <polygon fill="true" layer="200" grab_area="true" start_x="-1.600000" start_y="2.000000" width="0.000000">
     <segment end_x="-1.400000" end_y="2.000000" angle="0.000000"/>
     <segment end_x="-1.400000" end_y="2.700000" angle="0.000000"/>
     <segment end_x="-1.600000" end_y="2.700000" angle="0.000000"/>
     <segment end_x="-1.600000" end_y="2.000000" angle="0.000000"/>
    </polygon>
    <polygon fill="true" layer="200" grab_area="true" start_x="-1.100000" start_y="2.000000" width="0.000000">
     <segment end_x="-0.900000" end_y="2.000000" angle="0.000000"/>
     <segment end_x="-0.900000" end_y="2.700000" angle="0.000000"/>
     <segment end_x="-1.100000" end_y="2.700000" angle="0.000000"/>
     <segment end_x="-1.100000" end_y="2.000000" angle="0.000000"/>
    </polygon>
    <polygon fill="true" layer="200" grab_area="true" start_x="-0.600000" start_y="2.000000" width="0.000000">
     <segment end_x="-0.400000" end_y="2.000000" angle="0.000000"/>
     <segment end_x="-0.400000" end_y="2.700000" angle="0.000000"/>
     <segment end_x="-0.600000" end_y="2.700000" angle="0.000000"/>
     <segment end_x="-0.600000" end_y="2.000000" angle="0.000000"/>
    </polygon>
    <polygon fill="true" layer="200" grab_area="true" start_x="-0.100000" start_y="2.000000" width="0.000000">
     <segment end_x="0.100000" end_y="2.000000" angle="0.000000"/>
     <segment end_x="0.100000" end_y="2.700000" angle="0.000000"/>
     <segment end_x="-0.100000" end_y="2.700000" angle="0.000000"/>
     <segment end_x="-0.100000" end_y="2.000000" angle="0.000000"/>
    </polygon>
    <polygon fill="true" layer="200" grab_area="true" start_x="0.400000" start_y="2.000000" width="0.000000">
     <segment end_x="0.600000" end_y="2.000000" angle="0.000000"/>
     <segment end_x="0.600000" end_y="2.700000" angle="0.000000"/>
     <segment end_x="0.400000" end_y="2.700000" angle="0.000000"/>
     <segment end_x="0.400000" end_y="2.000000" angle="0.000000"/>
    </polygon>
    <polygon fill="true" layer="200" grab_area="true" start_x="0.900000" start_y="2.000000" width="0.000000">
     <segment end_x="1.100000" end_y="2.000000" angle="0.000000"/>
     <segment end_x="1.100000" end_y="2.700000" angle="0.000000"/>
     <segment end_x="0.900000" end_y="2.700000" angle="0.000000"/>
     <segment end_x="0.900000" end_y="2.000000" angle="0.000000"/>
    </polygon>
    <polygon fill="true" layer="200" grab_area="true" start_x="1.400000" start_y="2.000000" width="0.000000">
     <segment end_x="1.600000" end_y="2.000000" angle="0.000000"/>
     <segment end_x="1.600000" end_y="2.700000" angle="0.000000"/>
     <segment end_x="1.400000" end_y="2.700000" angle="0.000000"/>
     <segment end_x="1.400000" end_y="2.000000" angle="0.000000"/>
    </polygon>
    <polygon fill="true" layer="200" grab_area="true" start_x="1.900000" start_y="2.000000" width="0.000000">
     <segment end_x="2.100000" end_y="2.000000" angle="0.000000"/>
     <segment end_x="2.100000" end_y="2.700000" angle="0.000000"/>
     <segment end_x="1.900000" end_y="2.700000" angle="0.000000"/>
     <segment end_x="1.900000" end_y="2.000000" angle="0.000000"/>
    </polygon>
    <polygon fill="true" layer="300" grab_area="true" start_x="-5.650000" start_y="-0.200000" width="0.000000">
     <segment end_x="-3.250000" end_y="-0.200000" angle="0.000000"/>
     <segment end_x="-3.250000" end_y="2.000000" angle="0.000000"/>
     <segment end_x="-5.650000" end_y="2.000000" angle="0.000000"/>
     <segment end_x="-5.650000" end_y="-0.200000" angle="0.000000"/>
    </polygon>
    <polygon fill="true" layer="300" grab_area="true" start_x="-4.550000" start_y="-1.050000" width="0.000000">
     <segment end_x="-3.250000" end_y="-1.050000" angle="0.000000"/>
     <segment end_x="-3.250000" end_y="-0.200000" angle="0.000000"/>
     <segment end_x="-4.550000" end_y="-0.200000" angle="0.000000"/>
     <segment end_x="-4.550000" end_y="-1.050000" angle="0.000000"/>
    </polygon>
    <polygon fill="true" layer="300" grab_area="true" start_x="3.250000" start_y="-1.050000" width="0.000000">
     <segment end_x="4.550000" end_y="-1.050000" angle="0.000000"/>
     <segment end_x="4.550000" end_y="-0.200000" angle="0.000000"/>
     <segment end_x="3.250000" end_y="-0.200000" angle="0.000000"/>
     <segment end_x="3.250000" end_y="-1.050000" angle="0.000000"/>
    </polygon>
    <polygon fill="true" layer="300" grab_area="true" start_x="3.250000" start_y="-0.200000" width="0.000000">
     <segment end_x="5.650000" end_y="-0.200000" angle="0.000000"/>
     <segment end_x="5.650000" end_y="2.000000" angle="0.000000"/>
     <segment end_x="3.250000" end_y="2.000000" angle="0.000000"/>
     <segment end_x="3.250000" end_y="-0.200000" angle="0.000000"/>
    </polygon>
    <polygon fill="false" layer="260" grab_area="true" start_x="-2.500000" start_y="-1.250000" width="0.101600">
     <segment end_x="-2.500000" end_y="-1.200000" angle="0.000000"/>
     <segment end_x="-2.250000" end_y="-0.850000" angle="0.000000"/>
     <segment end_x="-2.000000" end_y="-1.200000" angle="0.000000"/>
     <segment end_x="-2.000000" end_y="-1.250000" angle="0.000000"/>
     <segment end_x="-2.500000" end_y="-1.250000" angle="0.000000"/>
    </polygon>
    <polygon fill="false" layer="200" grab_area="true" start_x="4.300000" start_y="1.900000" width="0.203200">
     <segment end_x="4.300000" end_y="-1.400000" angle="0.000000"/>
     <segment end_x="-4.300000" end_y="-1.400000" angle="0.000000"/>
     <segment end_x="-4.300000" end_y="1.900000" angle="0.000000"/>
     <segment end_x="4.300000" end_y="1.900000" angle="0.000000"/>
    </polygon>
    <text layer="240" height="2.500000" h_align="left" rotation="0.000000" v_align="bottom" x="-5.330000" y="3.270000">${CMP::NAME}</text>
    <text layer="250" height="2.000000" h_align="left" rotation="0.000000" v_align="bottom" x="-5.330000" y="-5.620000">${CMP::VALUE}</text>
    <pad type="smt_rect" height="0.800000" smt_side="top" width="0.300000" uuid="abde0033-cfdb-4d48-8ea4-52fefecf4346" rotation="0.000000" tht_drill="0.000000" x="0.500000" y="2.500000"/>
    <pad type="smt_rect" height="0.800000" smt_side="top" width="0.300000" uuid="eee4a569-1423-4c2d-9809-6bd5a86bb5f2" rotation="0.000000" tht_drill="0.000000" x="-1.000000" y="2.500000"/>
    <pad type="smt_rect" height="0.800000" smt_side="top" width="0.300000" uuid="0fb080ec-e02c-481d-8cb6-83b3d9ecc712" rotation="0.000000" tht_drill="0.000000" x="-2.000000" y="2.500000"/>
    <pad type="smt_rect" height="0.800000" smt_side="top" width="0.300000" uuid="4407dd8e-b1ca-46a5-8e4a-3262d76e4e5c" rotation="0.000000" tht_drill="0.000000" x="1.500000" y="2.500000"/>
    <pad type="smt_rect" height="0.800000" smt_side="top" width="0.300000" uuid="f705a7b5-818c-49d7-a918-6da24a756cdc" rotation="0.000000" tht_drill="0.000000" x="1.000000" y="2.500000"/>
    <pad type="smt_rect" height="0.800000" smt_side="top" width="0.300000" uuid="eb7010a3-1e93-44b8-8425-d56328a282f2" rotation="0.000000" tht_drill="0.000000" x="-0.500000" y="2.500000"/>
    <pad type="smt_rect" height="0.800000" smt_side="top" width="0.300000" uuid="bdd0e33a-1261-4e7e-bec9-f5c49a935fe1" rotation="0.000000" tht_drill="0.000000" x="0.000000" y="2.500000"/>
    <pad type="smt_rect" height="0.800000" smt_side="top" width="0.300000" uuid="20401992-0b8f-4b57-acbf-b82c2c710a41" rotation="0.000000" tht_drill="0.000000" x="2.000000" y="2.500000"/>
    <pad type="smt_rect" height="0.800000" smt_side="top" width="0.300000" uuid="98a572e0-08a1-49eb-b899-615c5ecd76ef" rotation="0.000000" tht_drill="0.000000" x="-1.500000" y="2.500000"/>
   </geometry>
  </footprint>
 </footprints>
</package>
