<?xml version='1.0' encoding='UTF-8' standalone='yes'?>
<package version="0">
 <meta>
  <uuid>b8f85589-de3e-4797-afd0-9fdbb77a2c87</uuid>
  <version>0.1</version>
  <author>LibrePCB</author>
  <created>2015-12-20T22:10:49Z</created>
  <last_modified>2015-12-20T22:10:49Z</last_modified>
  <name locale="en_US">2,54/1,1</name>
  <description locale="en_US">&lt;b>THROUGH-HOLE PAD&lt;/b>

This element was automatically imported from Eagle
Filepath: wirepad.lbr
Name: 2,54/1,1
NOTE: Remove this text after manual rework!</description>
  <keywords locale="en_US"></keywords>
 </meta>
 <pads>
  <pad uuid="b09a5602-f718-4b21-b837-4df8440d34a0">1</pad>
 </pads>
 <footprints default="0fcfa381-a7f6-4a8e-9606-9cfbad19ae71">
  <footprint uuid="0fcfa381-a7f6-4a8e-9606-9cfbad19ae71">
   <name locale="en_US">default</name>
   <description locale="en_US"></description>
   <geometry>
    <polygon fill="false" start_x="1.270000" start_y="1.270000" layer="260" width="0.152400" grab_area="true">
     <segment end_x="1.270000" end_y="0.762000" angle="0.000000"/>
    </polygon>
    <polygon fill="false" start_x="1.270000" start_y="1.270000" layer="260" width="0.152400" grab_area="true">
     <segment end_x="0.762000" end_y="1.270000" angle="0.000000"/>
    </polygon>
    <polygon fill="false" start_x="-1.270000" start_y="1.270000" layer="260" width="0.152400" grab_area="true">
     <segment end_x="-1.270000" end_y="0.762000" angle="0.000000"/>
    </polygon>
    <polygon fill="false" start_x="-1.270000" start_y="1.270000" layer="260" width="0.152400" grab_area="true">
     <segment end_x="-0.762000" end_y="1.270000" angle="0.000000"/>
    </polygon>
    <polygon fill="false" start_x="-1.270000" start_y="-1.270000" layer="260" width="0.152400" grab_area="true">
     <segment end_x="-1.270000" end_y="-0.762000" angle="0.000000"/>
    </polygon>
    <polygon fill="false" start_x="-1.270000" start_y="-1.270000" layer="260" width="0.152400" grab_area="true">
     <segment end_x="-0.762000" end_y="-1.270000" angle="0.000000"/>
    </polygon>
    <polygon fill="false" start_x="1.270000" start_y="-1.270000" layer="260" width="0.152400" grab_area="true">
     <segment end_x="0.762000" end_y="-1.270000" angle="0.000000"/>
    </polygon>
    <polygon fill="false" start_x="1.270000" start_y="-1.270000" layer="260" width="0.152400" grab_area="true">
     <segment end_x="1.270000" end_y="-0.762000" angle="0.000000"/>
    </polygon>
    <text x="-1.270000" y="1.524000" rotation="0.000000" layer="240" h_align="left" height="2.500000" v_align="bottom">${CMP::NAME}</text>
    <text x="0.000000" y="1.000000" rotation="0.000000" layer="250" h_align="left" height="2.000000" v_align="bottom">${CMP::VALUE}</text>
    <ellipse fill="false" x="0.000000" radius_x="1.016000" y="0.000000" radius_y="1.016000" rotation="0.000000" layer="200" width="0.152400" grab_area="true"/>
    <pad x="0.000000" y="0.000000" shape="octagon" drill="1.117600" rotation="0.000000" height="2.540000" uuid="b09a5602-f718-4b21-b837-4df8440d34a0" width="2.540000" technology="tht"/>
   </geometry>
  </footprint>
 </footprints>
</package>
