<?xml version='1.0' encoding='UTF-8' standalone='yes'?>
<package version="0">
 <meta>
  <uuid>{5a26d797-610b-42a2-8483-bf8020df06d0}</uuid>
  <version>0.1</version>
  <author>LibrePCB</author>
  <created>2015-12-20T22:10:36Z</created>
  <last_modified>2015-12-20T22:10:36Z</last_modified>
  <name locale="en_US">FE06W</name>
  <description locale="en_US">&lt;b>FEMALE HEADER&lt;/b>

This element was automatically imported from Eagle
Filepath: con-lsta.lbr
Name: FE06W
NOTE: Remove this text after manual rework!</description>
  <keywords locale="en_US"/>
 </meta>
 <pads>
  <pad uuid="{731c6146-b31f-49ac-a576-0f4c1de7b3dc}">1</pad>
  <pad uuid="{d469d5bd-93ef-4db1-b8f8-a7929553f019}">2</pad>
  <pad uuid="{468394dc-c650-47c8-b7bb-d6cdaaf8aa9e}">3</pad>
  <pad uuid="{bcbb7dff-7dd5-40a8-8103-75affd2d28c1}">4</pad>
  <pad uuid="{cf977890-01f7-4deb-be8a-271e639515c5}">5</pad>
  <pad uuid="{aca7afb3-a926-4952-aec8-985ade57cfb7}">6</pad>
 </pads>
 <footprints>
  <footprint default="true" uuid="{4c935af3-24a8-449a-a6b9-e22be5d3f0e4}">
   <name locale="en_US">default</name>
   <description locale="en_US"></description>
   <geometry>
    <polygon width="0.152400" start_x="-7.620000" start_y="1.016000" fill="false" grab_area="true" layer="260">
     <segment end_x="-7.620000" end_y="1.524000" angle="0.000000"/>
    </polygon>
    <polygon width="0.152400" start_x="-7.620000" start_y="1.524000" fill="false" grab_area="true" layer="260">
     <segment end_x="-7.620000" end_y="8.890000" angle="0.000000"/>
    </polygon>
    <polygon width="0.152400" start_x="-7.620000" start_y="8.890000" fill="false" grab_area="true" layer="260">
     <segment end_x="-5.461000" end_y="8.890000" angle="0.000000"/>
    </polygon>
    <polygon width="0.152400" start_x="-5.461000" start_y="8.890000" fill="false" grab_area="true" layer="260">
     <segment end_x="-5.080000" end_y="8.890000" angle="0.000000"/>
    </polygon>
    <polygon width="0.152400" start_x="-5.080000" start_y="8.890000" fill="false" grab_area="true" layer="260">
     <segment end_x="-4.699000" end_y="8.890000" angle="0.000000"/>
    </polygon>
    <polygon width="0.152400" start_x="-4.699000" start_y="8.890000" fill="false" grab_area="true" layer="260">
     <segment end_x="-2.921000" end_y="8.890000" angle="0.000000"/>
    </polygon>
    <polygon width="0.152400" start_x="-2.921000" start_y="8.890000" fill="false" grab_area="true" layer="260">
     <segment end_x="-2.540000" end_y="8.890000" angle="0.000000"/>
    </polygon>
    <polygon width="0.152400" start_x="-2.540000" start_y="8.890000" fill="false" grab_area="true" layer="260">
     <segment end_x="-2.159000" end_y="8.890000" angle="0.000000"/>
    </polygon>
    <polygon width="0.152400" start_x="-2.159000" start_y="8.890000" fill="false" grab_area="true" layer="260">
     <segment end_x="-0.381000" end_y="8.890000" angle="0.000000"/>
    </polygon>
    <polygon width="0.152400" start_x="-0.381000" start_y="8.890000" fill="false" grab_area="true" layer="260">
     <segment end_x="0.000000" end_y="8.890000" angle="0.000000"/>
    </polygon>
    <polygon width="0.152400" start_x="0.000000" start_y="8.890000" fill="false" grab_area="true" layer="260">
     <segment end_x="0.381000" end_y="8.890000" angle="0.000000"/>
    </polygon>
    <polygon width="0.152400" start_x="0.381000" start_y="8.890000" fill="false" grab_area="true" layer="260">
     <segment end_x="2.159000" end_y="8.890000" angle="0.000000"/>
    </polygon>
    <polygon width="0.152400" start_x="2.159000" start_y="8.890000" fill="false" grab_area="true" layer="260">
     <segment end_x="2.540000" end_y="8.890000" angle="0.000000"/>
    </polygon>
    <polygon width="0.152400" start_x="2.540000" start_y="8.890000" fill="false" grab_area="true" layer="260">
     <segment end_x="2.921000" end_y="8.890000" angle="0.000000"/>
    </polygon>
    <polygon width="0.152400" start_x="2.921000" start_y="8.890000" fill="false" grab_area="true" layer="260">
     <segment end_x="4.699000" end_y="8.890000" angle="0.000000"/>
    </polygon>
    <polygon width="0.152400" start_x="5.080000" start_y="8.890000" fill="false" grab_area="true" layer="260">
     <segment end_x="5.080000" end_y="1.524000" angle="0.000000"/>
    </polygon>
    <polygon width="0.152400" start_x="-7.620000" start_y="1.524000" fill="false" grab_area="true" layer="260">
     <segment end_x="-5.461000" end_y="1.524000" angle="0.000000"/>
    </polygon>
    <polygon width="0.152400" start_x="-5.461000" start_y="1.524000" fill="false" grab_area="true" layer="260">
     <segment end_x="-5.080000" end_y="1.524000" angle="0.000000"/>
    </polygon>
    <polygon width="0.152400" start_x="-5.080000" start_y="1.524000" fill="false" grab_area="true" layer="260">
     <segment end_x="-4.699000" end_y="1.524000" angle="0.000000"/>
    </polygon>
    <polygon width="0.152400" start_x="-4.699000" start_y="1.524000" fill="false" grab_area="true" layer="260">
     <segment end_x="-2.921000" end_y="1.524000" angle="0.000000"/>
    </polygon>
    <polygon width="0.152400" start_x="-2.921000" start_y="1.524000" fill="false" grab_area="true" layer="260">
     <segment end_x="-2.540000" end_y="1.524000" angle="0.000000"/>
    </polygon>
    <polygon width="0.152400" start_x="-2.540000" start_y="1.524000" fill="false" grab_area="true" layer="260">
     <segment end_x="-2.159000" end_y="1.524000" angle="0.000000"/>
    </polygon>
    <polygon width="0.152400" start_x="-2.159000" start_y="1.524000" fill="false" grab_area="true" layer="260">
     <segment end_x="-0.381000" end_y="1.524000" angle="0.000000"/>
    </polygon>
    <polygon width="0.152400" start_x="-0.381000" start_y="1.524000" fill="false" grab_area="true" layer="260">
     <segment end_x="0.000000" end_y="1.524000" angle="0.000000"/>
    </polygon>
    <polygon width="0.152400" start_x="0.000000" start_y="1.524000" fill="false" grab_area="true" layer="260">
     <segment end_x="0.381000" end_y="1.524000" angle="0.000000"/>
    </polygon>
    <polygon width="0.152400" start_x="0.381000" start_y="1.524000" fill="false" grab_area="true" layer="260">
     <segment end_x="2.159000" end_y="1.524000" angle="0.000000"/>
    </polygon>
    <polygon width="0.152400" start_x="2.159000" start_y="1.524000" fill="false" grab_area="true" layer="260">
     <segment end_x="2.540000" end_y="1.524000" angle="0.000000"/>
    </polygon>
    <polygon width="0.152400" start_x="2.540000" start_y="1.524000" fill="false" grab_area="true" layer="260">
     <segment end_x="2.921000" end_y="1.524000" angle="0.000000"/>
    </polygon>
    <polygon width="0.152400" start_x="2.921000" start_y="1.524000" fill="false" grab_area="true" layer="260">
     <segment end_x="4.699000" end_y="1.524000" angle="0.000000"/>
    </polygon>
    <polygon width="0.152400" start_x="4.699000" start_y="1.524000" fill="false" grab_area="true" layer="260">
     <segment end_x="5.080000" end_y="1.524000" angle="0.000000"/>
    </polygon>
    <polygon width="0.152400" start_x="2.540000" start_y="8.890000" fill="false" grab_area="true" layer="260">
     <segment end_x="2.540000" end_y="1.524000" angle="0.000000"/>
    </polygon>
    <polygon width="0.152400" start_x="0.000000" start_y="8.890000" fill="false" grab_area="true" layer="260">
     <segment end_x="0.000000" end_y="1.524000" angle="0.000000"/>
    </polygon>
    <polygon width="0.152400" start_x="-2.540000" start_y="8.890000" fill="false" grab_area="true" layer="260">
     <segment end_x="-2.540000" end_y="1.524000" angle="0.000000"/>
    </polygon>
    <polygon width="0.152400" start_x="-5.080000" start_y="8.890000" fill="false" grab_area="true" layer="260">
     <segment end_x="-5.080000" end_y="1.524000" angle="0.000000"/>
    </polygon>
    <polygon width="0.050800" start_x="-5.461000" start_y="8.890000" fill="false" grab_area="true" layer="260">
     <segment end_x="-5.461000" end_y="1.524000" angle="0.000000"/>
    </polygon>
    <polygon width="0.050800" start_x="-4.699000" start_y="8.890000" fill="false" grab_area="true" layer="260">
     <segment end_x="-4.699000" end_y="1.524000" angle="0.000000"/>
    </polygon>
    <polygon width="0.050800" start_x="-2.921000" start_y="8.890000" fill="false" grab_area="true" layer="260">
     <segment end_x="-2.921000" end_y="1.524000" angle="0.000000"/>
    </polygon>
    <polygon width="0.050800" start_x="-2.159000" start_y="8.890000" fill="false" grab_area="true" layer="260">
     <segment end_x="-2.159000" end_y="1.524000" angle="0.000000"/>
    </polygon>
    <polygon width="0.050800" start_x="-0.381000" start_y="8.890000" fill="false" grab_area="true" layer="260">
     <segment end_x="-0.381000" end_y="1.524000" angle="0.000000"/>
    </polygon>
    <polygon width="0.050800" start_x="0.381000" start_y="8.890000" fill="false" grab_area="true" layer="260">
     <segment end_x="0.381000" end_y="1.524000" angle="0.000000"/>
    </polygon>
    <polygon width="0.152400" start_x="2.159000" start_y="8.890000" fill="false" grab_area="true" layer="260">
     <segment end_x="2.159000" end_y="1.524000" angle="0.000000"/>
    </polygon>
    <polygon width="0.050800" start_x="2.921000" start_y="8.890000" fill="false" grab_area="true" layer="260">
     <segment end_x="2.921000" end_y="1.524000" angle="0.000000"/>
    </polygon>
    <polygon width="0.050800" start_x="4.699000" start_y="8.890000" fill="false" grab_area="true" layer="260">
     <segment end_x="4.699000" end_y="1.524000" angle="0.000000"/>
    </polygon>
    <polygon width="0.152400" start_x="4.699000" start_y="8.890000" fill="false" grab_area="true" layer="260">
     <segment end_x="5.080000" end_y="8.890000" angle="0.000000"/>
    </polygon>
    <polygon width="0.152400" start_x="5.080000" start_y="8.890000" fill="false" grab_area="true" layer="260">
     <segment end_x="5.461000" end_y="8.890000" angle="0.000000"/>
    </polygon>
    <polygon width="0.152400" start_x="5.461000" start_y="8.890000" fill="false" grab_area="true" layer="260">
     <segment end_x="7.620000" end_y="8.890000" angle="0.000000"/>
    </polygon>
    <polygon width="0.050800" start_x="5.461000" start_y="8.890000" fill="false" grab_area="true" layer="260">
     <segment end_x="5.461000" end_y="1.524000" angle="0.000000"/>
    </polygon>
    <polygon width="0.152400" start_x="7.620000" start_y="8.890000" fill="false" grab_area="true" layer="260">
     <segment end_x="7.620000" end_y="1.524000" angle="0.000000"/>
    </polygon>
    <polygon width="0.152400" start_x="7.620000" start_y="1.524000" fill="false" grab_area="true" layer="260">
     <segment end_x="7.620000" end_y="1.016000" angle="0.000000"/>
    </polygon>
    <polygon width="0.152400" start_x="-7.620000" start_y="1.016000" fill="false" grab_area="true" layer="260">
     <segment end_x="7.620000" end_y="1.016000" angle="0.000000"/>
    </polygon>
    <polygon width="0.152400" start_x="5.080000" start_y="1.524000" fill="false" grab_area="true" layer="260">
     <segment end_x="5.461000" end_y="1.524000" angle="0.000000"/>
    </polygon>
    <polygon width="0.152400" start_x="5.461000" start_y="1.524000" fill="false" grab_area="true" layer="260">
     <segment end_x="7.620000" end_y="1.524000" angle="0.000000"/>
    </polygon>
    <polygon width="0.000000" start_x="-6.604000" start_y="0.000000" fill="true" grab_area="true" layer="200">
     <segment end_x="-6.096000" end_y="0.000000" angle="0.000000"/>
     <segment end_x="-6.096000" end_y="1.016000" angle="0.000000"/>
     <segment end_x="-6.604000" end_y="1.016000" angle="0.000000"/>
     <segment end_x="-6.604000" end_y="0.000000" angle="0.000000"/>
    </polygon>
    <polygon width="0.000000" start_x="-4.064000" start_y="0.000000" fill="true" grab_area="true" layer="200">
     <segment end_x="-3.556000" end_y="0.000000" angle="0.000000"/>
     <segment end_x="-3.556000" end_y="1.016000" angle="0.000000"/>
     <segment end_x="-4.064000" end_y="1.016000" angle="0.000000"/>
     <segment end_x="-4.064000" end_y="0.000000" angle="0.000000"/>
    </polygon>
    <polygon width="0.000000" start_x="-1.524000" start_y="0.000000" fill="true" grab_area="true" layer="200">
     <segment end_x="-1.016000" end_y="0.000000" angle="0.000000"/>
     <segment end_x="-1.016000" end_y="1.016000" angle="0.000000"/>
     <segment end_x="-1.524000" end_y="1.016000" angle="0.000000"/>
     <segment end_x="-1.524000" end_y="0.000000" angle="0.000000"/>
    </polygon>
    <polygon width="0.000000" start_x="1.016000" start_y="0.000000" fill="true" grab_area="true" layer="200">
     <segment end_x="1.524000" end_y="0.000000" angle="0.000000"/>
     <segment end_x="1.524000" end_y="1.016000" angle="0.000000"/>
     <segment end_x="1.016000" end_y="1.016000" angle="0.000000"/>
     <segment end_x="1.016000" end_y="0.000000" angle="0.000000"/>
    </polygon>
    <polygon width="0.000000" start_x="3.556000" start_y="0.000000" fill="true" grab_area="true" layer="200">
     <segment end_x="4.064000" end_y="0.000000" angle="0.000000"/>
     <segment end_x="4.064000" end_y="1.016000" angle="0.000000"/>
     <segment end_x="3.556000" end_y="1.016000" angle="0.000000"/>
     <segment end_x="3.556000" end_y="0.000000" angle="0.000000"/>
    </polygon>
    <polygon width="0.000000" start_x="6.096000" start_y="0.000000" fill="true" grab_area="true" layer="200">
     <segment end_x="6.604000" end_y="0.000000" angle="0.000000"/>
     <segment end_x="6.604000" end_y="1.016000" angle="0.000000"/>
     <segment end_x="6.096000" end_y="1.016000" angle="0.000000"/>
     <segment end_x="6.096000" end_y="0.000000" angle="0.000000"/>
    </polygon>
    <text x="-7.620000" height="2.500000" y="-2.540000" rotation="0.000000" h_align="left" v_align="bottom" layer="240">${CMP::NAME}</text>
    <text x="-5.842000" height="2.000000" y="2.032000" rotation="90.000000" h_align="left" v_align="bottom" layer="250">${CMP::VALUE}</text>
    <text x="-3.175000" height="2.540000" y="2.540000" rotation="90.000000" h_align="left" v_align="bottom" layer="260">2</text>
    <text x="6.985000" height="2.540000" y="2.540000" rotation="90.000000" h_align="left" v_align="bottom" layer="260">6</text>
    <text x="-0.635000" height="2.540000" y="2.540000" rotation="90.000000" h_align="left" v_align="bottom" layer="260">3</text>
    <text x="1.905000" height="2.540000" y="2.540000" rotation="90.000000" h_align="left" v_align="bottom" layer="260">4</text>
    <text x="4.445000" height="2.540000" y="2.540000" rotation="90.000000" h_align="left" v_align="bottom" layer="260">5</text>
    <pad smt_side="top" width="3.251200" x="-3.810000" height="1.625600" y="0.000000" rotation="90.000000" type="tht_round" uuid="{d469d5bd-93ef-4db1-b8f8-a7929553f019}" tht_drill="0.812800"/>
    <pad smt_side="top" width="3.251200" x="6.350000" height="1.625600" y="0.000000" rotation="90.000000" type="tht_round" uuid="{aca7afb3-a926-4952-aec8-985ade57cfb7}" tht_drill="0.812800"/>
    <pad smt_side="top" width="3.251200" x="-6.350000" height="1.625600" y="0.000000" rotation="90.000000" type="tht_round" uuid="{731c6146-b31f-49ac-a576-0f4c1de7b3dc}" tht_drill="0.812800"/>
    <pad smt_side="top" width="3.251200" x="-1.270000" height="1.625600" y="0.000000" rotation="90.000000" type="tht_round" uuid="{468394dc-c650-47c8-b7bb-d6cdaaf8aa9e}" tht_drill="0.812800"/>
    <pad smt_side="top" width="3.251200" x="1.270000" height="1.625600" y="0.000000" rotation="90.000000" type="tht_round" uuid="{bcbb7dff-7dd5-40a8-8103-75affd2d28c1}" tht_drill="0.812800"/>
    <pad smt_side="top" width="3.251200" x="3.810000" height="1.625600" y="0.000000" rotation="90.000000" type="tht_round" uuid="{cf977890-01f7-4deb-be8a-271e639515c5}" tht_drill="0.812800"/>
   </geometry>
  </footprint>
 </footprints>
</package>
