<?xml version='1.0' encoding='UTF-8' standalone='yes'?>
<package version="0">
 <meta>
  <uuid>{db61e2de-e766-4914-bb34-66c1f34e5c2d}</uuid>
  <version>0.1</version>
  <author>LibrePCB</author>
  <created>2015-12-20T22:10:49Z</created>
  <last_modified>2015-12-20T22:10:49Z</last_modified>
  <name locale="en_US">L2825P</name>
  <description locale="en_US">&lt;b>INDUCTOR&lt;/b>&lt;p>
precision wire wound

This element was automatically imported from Eagle
Filepath: rcl.lbr
Name: L2825P
NOTE: Remove this text after manual rework!</description>
  <keywords locale="en_US"/>
 </meta>
 <pads>
  <pad uuid="{5703a27b-a7c6-4829-9106-0861e3f21dd3}">1</pad>
  <pad uuid="{06beabc1-d196-4868-ba5f-3bbec55432e0}">2</pad>
 </pads>
 <footprints>
  <footprint default="true" uuid="{459c6138-45a3-46a1-add6-ee17558178f3}">
   <name locale="en_US">default</name>
   <description locale="en_US"></description>
   <geometry>
    <polygon width="0.101600" start_x="-0.762000" start_y="1.200000" fill="false" grab_area="true" layer="200">
     <segment end_x="0.762000" end_y="1.200000" angle="0.000000"/>
    </polygon>
    <polygon width="0.101600" start_x="-0.762000" start_y="-1.213000" fill="false" grab_area="true" layer="200">
     <segment end_x="0.762000" end_y="-1.213000" angle="0.000000"/>
    </polygon>
    <polygon width="0.101600" start_x="1.340000" start_y="-0.965000" fill="false" grab_area="true" layer="200">
     <segment end_x="1.340000" end_y="0.965000" angle="0.000000"/>
    </polygon>
    <polygon width="0.101600" start_x="-1.340000" start_y="0.965000" fill="false" grab_area="true" layer="200">
     <segment end_x="-1.340000" end_y="-0.965000" angle="0.000000"/>
    </polygon>
    <polygon width="0.000000" start_x="0.736600" start_y="-1.270000" fill="true" grab_area="true" layer="200">
     <segment end_x="1.320800" end_y="-1.270000" angle="0.000000"/>
     <segment end_x="1.320800" end_y="1.270000" angle="0.000000"/>
     <segment end_x="0.736600" end_y="1.270000" angle="0.000000"/>
     <segment end_x="0.736600" end_y="-1.270000" angle="0.000000"/>
    </polygon>
    <polygon width="0.000000" start_x="-1.320800" start_y="-1.270000" fill="true" grab_area="true" layer="200">
     <segment end_x="-0.736600" end_y="-1.270000" angle="0.000000"/>
     <segment end_x="-0.736600" end_y="1.270000" angle="0.000000"/>
     <segment end_x="-1.320800" end_y="1.270000" angle="0.000000"/>
     <segment end_x="-1.320800" end_y="-1.270000" angle="0.000000"/>
    </polygon>
    <polygon width="0.000000" start_x="-0.300000" start_y="-0.700000" fill="true" grab_area="true" layer="220">
     <segment end_x="0.300000" end_y="-0.700000" angle="0.000000"/>
     <segment end_x="0.300000" end_y="0.700000" angle="0.000000"/>
     <segment end_x="-0.300000" end_y="0.700000" angle="0.000000"/>
     <segment end_x="-0.300000" end_y="-0.700000" angle="0.000000"/>
    </polygon>
    <polygon width="0.050800" start_x="2.473000" start_y="-1.483000" fill="false" grab_area="true" layer="280">
     <segment end_x="2.473000" end_y="1.483000" angle="0.000000"/>
     <segment end_x="-2.473000" end_y="1.483000" angle="0.000000"/>
     <segment end_x="-2.473000" end_y="-1.483000" angle="0.000000"/>
     <segment end_x="2.473000" end_y="-1.483000" angle="0.000000"/>
    </polygon>
    <text x="-1.905000" height="2.500000" y="1.905000" rotation="0.000000" h_align="left" v_align="bottom" layer="240">${CMP::NAME}</text>
    <text x="-1.905000" height="2.000000" y="-3.175000" rotation="0.000000" h_align="left" v_align="bottom" layer="250">${CMP::VALUE}</text>
    <ellipse width="0.152400" radius_x="0.660400" x="0.000000" radius_y="0.660400" y="0.000000" fill="false" grab_area="true" rotation="0.000000" layer="200"/>
    <pad smt_side="top" width="1.400000" x="-1.200000" height="2.400000" y="0.000000" rotation="0.000000" type="smt_rect" uuid="{5703a27b-a7c6-4829-9106-0861e3f21dd3}" tht_drill="0.000000"/>
    <pad smt_side="top" width="1.400000" x="1.200000" height="2.400000" y="0.000000" rotation="0.000000" type="smt_rect" uuid="{06beabc1-d196-4868-ba5f-3bbec55432e0}" tht_drill="0.000000"/>
   </geometry>
  </footprint>
 </footprints>
</package>
